setup.py
bm_common.egg-info/PKG-INFO
bm_common.egg-info/SOURCES.txt
bm_common.egg-info/dependency_links.txt
bm_common.egg-info/not-zip-safe
bm_common.egg-info/top_level.txt
src/__init__.py
src/decorators.py
src/dependency.py
src/file_tools.py
src/id_map.py
src/list.py
src/memoize.py
src/mm_hash.c
src/retry.py
src/settings.py
src/shell.py
src/sun.py
src/version.py
src/maths/__init__.py
src/maths/deterministic_random.py
src/maths/floats.py
src/maths/gaussian.py
src/maths/math.py
src/maths/misc.py
src/maths/numpy_helper.py
src/maths/percentage.py
src/maths/running_average.py