Metadata-Version: 1.0
Name: bm-common
Version: 0.0.1b
Summary: This is shared code between projects
Home-page: UNKNOWN
Author: Alex Toney
Author-email: toneyalex@gmail.com
License: GPL
Keywords: misc utils extra
Platform: UNKNOWN
